32Bit_SingleCycle/Alu_Core.v
module Alu_Core(
	A,
	B,
	alu_control,
	result,
	zero
    );

input [31:0] A;
input [31:0] B;
input [2:0] alu_control;
output reg [31:0] result;
output wire zero;

assign zero = !(|result);  //logical negation bit-wise OR result; used for BEQ 

always @ (*)
begin
	case(alu_control)
	3'h2: result = A + B;  // add ALU control input
	3'h6: result = A - B;  // subtract ALU control input
	3'h0: result = A & B;  // AND ALU control input
	3'h1: result = A | B;  // OR ALU control input
	3'h4: result = ~(A | B);  // NOR ALU control input
	3'h7: result = (A < B);  // set on less than ALU control input
	default: result = A + B;
	endcase
end
endmodule

32Bit_SingleCycle/Alu_Control.v
module Alu_Control(
	opcode,
	func_field,
	alu_control
    );
	 
input [5:0] opcode;
input [5:0] func_field;
output reg [2:0] alu_control;
reg [2:0] func_code;

always @ (*)
begin
	case (func_field)  //for R-type instructions; other instructions they are don't cares
	/* Desired ALU action*/
	6'h20: func_code = 3'h2;  // add
	6'h22: func_code = 3'h6;  // subtract
	6'h24: func_code = 3'h0;  // AND
	6'h25: func_code = 3'h1;  // OR
	6'h27: func_code = 3'h4;  // NOR
	6'h2A: func_code = 3'h7;  // set on less than (SLT)
	default: func_code = 3'h0; // add when LW or SW since don't cares
	endcase  //

	case (opcode)
	6'h00: alu_control = func_code;  // for all R-type instruction
	6'h04: alu_control = 3'h1;  // beq 
	6'h23: alu_control = 3'h0;  // lw
	6'h2B: alu_control = 3'h0;  // sw 
	default: alu_control = 3'h0;
	endcase
end
endmodule

32Bit_SingleCycle/Alu_Top.v
module Alu_Top(
	opcode,
	func_field,
	A,
	B,
	result,
	zero
    );

input [5:0] opcode;
input [5:0] func_field;
input [31:0] A;
input [31:0] B;
output [31:0] result;
output zero;
wire [2:0] alu_control;

Alu_Control alu_ctrlr_inst (
.opcode (opcode),
.func_field (func_field),
.alu_control (alu_control)
);

Alu_Core alu_core_inst (
.A (A),
.B (B),
.alu_control (alu_control),
.result (result),
.zero (zero)
);

endmodule

32Bit_SingleCycle/Alu_Top_tb.v
module Alu_Top_tb;

// Inputs
reg [5:0] opcode;
reg [5:0] func_field;
reg [31:0] A;
reg [31:0] B;

// Outputs
wire [31:0] result;
wire zero;

// Instantiate the Unit Under Test (UUT)
Alu_Top uut (
	.opcode(opcode), 
	.func_field(func_field), 
	.A(A), 
	.B(B), 
	.result(result),
	.zero(zero)
);

initial begin
	$dumpfile("alu_top.vcd");
	$dumpvars();

	// Initialize Inputs
	opcode = 0;
	func_field = 0;
	A = 0;
	B = 0;
	
	#30; // ADD
	A=32'h2222; B=32'h1111;
	opcode=6'h00;func_field=6'h20; 
	#30; // AND
	opcode=6'h00;func_field=6'h24;
	#30; // LW
	opcode=6'h23;func_field=6'h00;
	#30; // BEQ
	A=31'h5555; B=32'h5555;
	opcode=6'h04;func_field=6'h00;
	#30; // SLT
	A=32'h1111; B=32'h2222;
	opcode=6'h00;func_field=6'h2A;
	#30; // OR
	opcode=6'h00;func_field=6'h25;
	#30; // OR
	A=32'h1111; B=32'h3333;
	#30; // OR
	A=32'h9210; B=32'h3338;
	#30; // NOR
	A=32'h1111; B=32'h2222;
	opcode=6'h00;func_field=6'h27;
	#30; // Subtract
	A=32'h2222; B=32'h1111;
	opcode=6'h00;func_field=6'h22;
	#30;
	$finish;
end
      
endmodule

test.vcd
$date
	Sat Dec 03 20:23:15 2022
$end
$version
	Icarus Verilog
$end
$timescale
	1s
$end
$scope module Alu_Top_tb $end
$var wire 1 ! zero $end
$var wire 32 " result [31:0] $end
$var reg 32 # A [31:0] $end
$var reg 32 $ B [31:0] $end
$var reg 6 % func_field [5:0] $end
$var reg 6 & opcode [5:0] $end
$scope module uut $end
$var wire 32 ' A [31:0] $end
$var wire 32 ( B [31:0] $end
$var wire 6 ) func_field [5:0] $end
$var wire 6 * opcode [5:0] $end
$var wire 1 ! zero $end
$var wire 32 + result [31:0] $end
$var wire 3 , alu_control [2:0] $end
$scope module alu_core_inst $end
$var wire 32 - A [31:0] $end
$var wire 32 . B [31:0] $end
$var wire 1 ! zero $end
$var wire 3 / alu_control [2:0] $end
$var reg 32 0 result [31:0] $end
$upscope $end
$scope module alu_ctrlr_inst $end
$var wire 6 1 func_field [5:0] $end
$var wire 6 2 opcode [5:0] $end
$var reg 3 3 alu_control [2:0] $end
$var reg 3 4 func_code [2:0] $end
$upscope $end
$upscope $end
$upscope $end
$enddefinitions $end
#0
$dumpvars
b0 4
b0 3
b0 2
b0 1
b0 0
b0 /
b0 .
b0 -
b0 ,
b0 +
b0 *
b0 )
b0 (
b0 '
b0 &
b0 %
b0 $
b0 #
b0 "
1!
$end
#30
0!
b11001100110011 "
b11001100110011 +
b11001100110011 0
b10 ,
b10 /
b10 3
b10 4
b100000 %
b100000 )
b100000 1
b1000100010001 $
b1000100010001 (
b1000100010001 .
b10001000100010 #
b10001000100010 '
b10001000100010 -
#60
1!
b0 "
b0 +
b0 0
b0 ,
b0 /
b0 3
b0 4
b100100 %
b100100 )
b100100 1
#90
b0 %
b0 )
b0 1
b100011 &
b100011 *
b100011 2
#120
b1 ,
b1 /
b1 3
0!
b101010101010101 "
b101010101010101 +
b101010101010101 0
b100 &
b100 *
b100 2
b101010101010101 $
b101010101010101 (
b101010101010101 .
b101010101010101 #
b101010101010101 '
b101010101010101 -
#150
b111 ,
b111 /
b111 3
b111 4
b1 "
b1 +
b1 0
b101010 %
b101010 )
b101010 1
b0 &
b0 *
b0 2
b10001000100010 $
b10001000100010 (
b10001000100010 .
b1000100010001 #
b1000100010001 '
b1000100010001 -
#180
b11001100110011 "
b11001100110011 +
b11001100110011 0
b1 ,
b1 /
b1 3
b1 4
b100101 %
b100101 )
b100101 1
#210
b11001100110011 $
b11001100110011 (
b11001100110011 .
#240
b1011001100111000 "
b1011001100111000 +
b1011001100111000 0
b11001100111000 $
b11001100111000 (
b11001100111000 .
b1001001000010000 #
b1001001000010000 '
b1001001000010000 -
#270
b100 ,
b100 /
b100 3
b100 4
b11111111111111111100110011001100 "
b11111111111111111100110011001100 +
b11111111111111111100110011001100 0
b100111 %
b100111 )
b100111 1
b10001000100010 $
b10001000100010 (
b10001000100010 .
b1000100010001 #
b1000100010001 '
b1000100010001 -
#300
b1000100010001 "
b1000100010001 +
b1000100010001 0
b110 ,
b110 /
b110 3
b110 4
b100010 %
b100010 )
b100010 1
b1000100010001 $
b1000100010001 (
b1000100010001 .
b10001000100010 #
b10001000100010 '
b10001000100010 -
